{"id": "105", "name": "Kth Smallest and Largest element in BST", "slug": "kth-smallest-and-largest-element-in-bst", "difficulty": "Medium", "category": "Binary Search Trees [Concept and Problems]", "subcategory": "Practice Problems", "links": {"article": "https://takeuforward.org/data-structure/kth-largest-smallest-element-in-binary-search-tree/", "youtube": "https://youtu.be/9TJYWh0adfk", "leetcode": "https://leetcode.com/problems/kth-smallest-element-in-a-bst/", "gfg": "https://practice.geeksforgeeks.org/problems/kth-smallest-element5635/1", "cn": "https://www.codingninjas.com/studio/problems/kth-smallest-node-in-bst_920441"}, "isPremium": false, "hasCpp": true, "statement": "<p>Given the <strong>root</strong> node of a binary search tree (BST) and an integer k.</p><p><br></p><p>Return the <strong>k</strong><sup><strong>th</strong></sup> <strong>smallest</strong> and <strong>largest</strong> value (1-indexed) of all values of the nodes in the tree.</p><p><br></p><p>Return the 1<sup>st</sup> integer as k<sup>th</sup> smallest and 2<sup>nd</sup> integer as k<sup>th</sup> largest in the returned array.</p>", "constraints": "<ul><li>The number of nodes in the tree is n.</li><li>1 &lt;= k &lt;= n &lt;= 10<sup>4</sup></li><li>0 &lt;= Node.val &lt;= 10<sup>5</sup></li></ul>", "starterCpp": "/**\n * Definition for a binary tree node.\n * struct TreeNode {\n *     int data;\n *     TreeNode *left;\n *     TreeNode *right;\n *      TreeNode(int val) : data(val) , left(nullptr) , right(nullptr) {}\n * };\n **/\n\nclass Solution {\npublic:\n\tvector<int> kLargesSmall(TreeNode* root,int k){\n\t\t//your code goes here\n\t}\n};", "languages": ["cpp", "java", "python", "javascript", "csharp", "go"], "examples": [{"input": "root = [3,1,4,null,2] , k = 1", "output": "[1, 4]", "explanation": "The 1st smallest value in given BST is 1. The 1st largest value in given BST is 4."}, {"input": "root = [5, 3, 6, 2, null, null, null, 1] , k = 3", "output": "[3, 3]", "explanation": "The 3rd smallest value in given BST is 3. The 3rd largest value in given BST is 3."}], "nowYourTurn": {"input": "root = [3,1,4,null,2] , k = 2", "options": ["[1, 2]", "[2, 3]", "[3, 4]", "[1, 3]"], "tcIndex": 2}, "testcases": [{"name": "Case 1", "inputs": {"k": "1", "root": "3 1 4 null 2"}, "expected": "[1, 4]"}, {"name": "Case 2", "inputs": {"k": "3", "root": "5 3 6 2 null null null 1"}, "expected": "[3, 3]"}, {"name": "Case 3", "inputs": {"k": "2", "root": "10 5 14 1 9 11 19"}, "expected": null}]}